{
  "business": [
    {
      "name": "Sushi Express",
      "address": "Polux 201, Contry Lux, 64860",
      "phone": 83577921,
      "membershipLevel": "Silver",
      "url": "https://sushiexpress.com.mx/",
      "image": "images/sushi-express-400x400.jpg"
    },
    {
      "name": "Porrua",
      "address": " Av Hacienda de Peñuelas 6771, Cumbres Las Palmas Residencial, 64610",
      "phone": 8150302256,
      "membershipLevel": "Silver",
      "url": "https://www.porrua.com.mx/",
      "image": "images/porrua-400x400.jpg"
    },
    {
      "name": "El Lindero",
      "address": "Degollado #770 Sur, Obispado, 64060",
      "phone": 8114155752,
      "membershipLevel": "Silver",
      "url": "https://www.ellindero.com/",
      "image": "images/lindero-400x400.jpg"
    },
    {
      "name": "PCEL",
      "address": "Av. Ignacio Morones Prieto 1101, Nuevo Repueblo, 64700",
      "phone": 8188656000,
      "membershipLevel": "Silver",
      "url": "https://www.pcel.com/",
      "image": "images/pcel-400x400.png"
    },
    {
      "name": "Mr Pampas Do Brasil",
      "address": "Av. Eugenio Garza Sada 3515, Contry, 64860",
      "phone": 8112343313,
      "membershipLevel": "Silver",
      "url": "https://www.ellindero.com/",
      "image": "images/pampas-400x400.jpg"
    },
    {
      "name": "Steren",
      "address": "Av. Francisco I. Madero 1467, Centro, 64000",
      "phone": 8183721371,
      "membershipLevel": "Silver",
      "url": "https://www.steren.com.mx/",
      "image": "images/steren-400x400.png"
    },
    {
      "name": "Devlyn",
      "address": " Av. Fundadores 101, Flor de Mayo, 66269 San Pedro Garza García, N.L.",
      "phone": 8181531100,
      "membershipLevel": "Silver",
      "url": "https://www.devlyn.com.mx/",
      "image": "images/devlyn-400x400.jpg"
    },
    {
      "name": "El Lingote Resturante",
      "address": "Av. Fundidora s/n Museo del Acero A.C, Obrera, 64010 Monterrey, N.L.",
      "phone": 8181917717,
      "membershipLevel": "Silver",
      "url": "https://www.ellingoterestaurante.com/",
      "image": "images/lingote-400x400.jpg"
    },
    {
      "name": "Imagen Dental",
      "address": "Av. Dr. José Eleuterio González 3036, Mitras Nte., 64320 Monterrey, N.L.",
      "phone": 8183707080,
      "membershipLevel": "Silver",
      "url": "https://www.imagendental.com/",
      "image": "images/imagen-dental-400x400.jpg"
    }
  ]
}